qf_common/__init__.py
qf_common/cache/__init__.py
qf_common/consts/__init__.py
qf_common/db/__init__.py
qf_common/db/client.py
qf_common/db/db_config.py
qf_common/db/settings.py
qf_common/ds/__init__.py
qf_common/finance/__init__.py
qf_common/finance/finance.py
qf_common/finance/nelson_siegel.py
qf_common/finance/ornstein_uhlenbeck.py
qf_common/finance/securities.py
qf_common/market/__init__.py
qf_common/py.typed
qf_common/s3tools/__init__.py
qf_common/s3tools/s3_tools.py
qf_common/timecal/__init__.py
qf_common/timecal/formatting.py
qf_common/timecal/generators.py
qf_common/timeseries/__init__.py
qf_common/utils/__init__.py
qf_common/utils/alerts.py
qf_common/utils/debug_utils.py
quantfox_common-0.1.15.dist-info/METADATA
quantfox_common-0.1.15.dist-info/WHEEL
quantfox_common-0.1.15.dist-info/RECORD
